{
    "required": true,
    "package": "com.overpoweredmobs.mixin",
    "compatibilityLevel": "JAVA_21",
    "mixins": [
        "MobAttributesMixin",
        "ExperienceMultiplierMixin",
        "DropMultiplierMixin",
        "PinataDespawnMixin",
        "CreeperAccessor",
        "LargeFireballMixin",
        "GhastChargeMixin",
        "PiglinHiveMixin",
        "ShulkerBulletMixin",
        "RabbitMixin",
        "StrongholdMobTriggerMixin",
        "GiantAIMixin",
        "WolfMixin",
        "EndermanMixin"
    ],
    "accessors": [
        "LargeFireballAccessor"
    ],
    "injectors": {
        "defaultRequire": 1
    }
}
